{
	"music": [
		["Stay Inside Me",         "OcularNebula", "7.56",  "535331", "Stay-Inside-Me.mp3",             0],
		["Stereo Madness",         "ForeverBound", "7.56",  "500476", "Stereo-Madness.mp3",             0],
		["Back on Track",          "DJVI",         "6.9",   "522654", "Back-On-Track.mp3",              0],
		["Polargeist",             "Step",         "4.25",  "523561", "Polargeist.mp3",                 0],
		["Dry Out",                "DJVI",         "5.25",  "498543", "Dry-Out.mp3",                    0],
		["Base After Base",        "DJVI",         "5.87",  "404997", "DJ_V.I.___Base_After_Base.mp3",  0],
		["Can't Let Go",           "DJVI",         "7.08",  "485351", "Cant-Let-Go.mp3",                0],
		["Jumper",                 "Waterflame",   "3.03",  "168734", "Jumper.mp3",                     0],
		["Time Machine",           "Waterflame",   "6.34",  "291458", "Waterflame___Time_machine.mp3",  0],
		["Cycles",                 "DJVI",         "7.06",  "529148", "Cycles.mp3",                     0],
		["xStep",                  "DJVI",         "7.34",  "516735", "xStep.mp3",                      0],
		["Clutterfunk",            "Waterflame",   "9.71",  "505816", "-Clutterfunk-.mp3",              0],
		["Theory of Everything",   "DJ-Nate",      "6.03",  "350290", "MToE.mp3",                       0],
		["Electroman Adventures",  "Waterflame",   "5.82",  "479319", "-Electroman-adventures-.mp3",    0],
		["Clubstep",               "DJ-Nate",      "6.31",  "396093", "naten3e222w.mp3",                0],
		["Electrodynamix",         "DJ-Nate",      "7.83",  "368392", "electrodynamix.mp3",             0],
		["Hexagon Force",          "Waterflame",   "9.69",  "568699", "-Hexagon-Force-.mp3",            0],
		["Blast Processing",       "Waterflame",   "10.73", "507560", "-BlastProcess-.mp3",             0],
		["Theory of Everything 2", "DJ-Nate",      "3.91",  "472925", "Theory-of-Everything-2.mp3",     0],
		["Geometrical Dominator",  "Waterflame",   "3.96",  "641172", "-Geometrical-Dominator-.mp3",    0],
		["Deadlocked",             "F-777",        "7.94",  "503731", "F-777---Deadlocked-Full.mp3",    0],
		["Fingerdash",             "MDK",          null,    null,     null,                             0],
		["The Seven Seas",         "F-777",        null,    null,     null,                             1],
		["Viking Arena",           "F-777",        null,    null,     null,                             1],
		["Airborne Robots",        "F-777",        null,    null,     null,                             1],
		["The Challenge",          "RobTop",       "0.53",  "633385", "Random-Song-06.mp3",             0],
		["Payload",                "Dex Arson",    "11.52", "589289", "-Payload-.mp3",                  2],
		["Beast Mode",             "Dex Arson",    "8.83",  "589874", "Beast-Mode.mp3",                 2],
		["Machina",                "Dex Arson",    "9.05",  "582310", "Machina.mp3",                    2],
		["Years",                  "Dex Arson",    "11.88", "582980", "Years.mp3",                      2],
		["Frontlines",             "Dex Arson",    "6.81",  "614535", "-Electro--Frontlines.mp3",       2],
		["Space Pirates",          "Waterflame",   "2.53",  "57239",  "newgrounds_space_.mp3",          2],
		["Striker",                "Waterflame",   "4.35",  "711933", "-Striker-.mp3",                  2],
		["Round 1",                "Dex Arson",    "8.3",   "585138", "Round-1.mp3",                    2],
		["Embers",                 "Dex Arson",    "9.62",  "691000", "Dex-Arson---Embers-Ft-Stac.mp3", 2],
		["Monster Dance Off",      "F-777",        null,    null,     null,                             2],
		["Press Start",            "MDK",          null,    null,     null,                             3],
		["Nock Em",                "Bossfight",    "8.08",  "782870", "Bossfight---Nock-Em.mp3",        3],
		["Power Trip",             "Boom Kitty",   "8.7",   "780702", "Power-Trip--Geometry-Dash-.mp3", 3]
	],

	"difficulties": {
		"easy": "1",
		"normal": "2",
		"hard": "3",
		"harder": "4",
		"insane": "5",
		"demon": "-2",
		"easydemon": "-2&demonFilter=1",
		"mediumdemon": "-2&demonFilter=2",
		"harddemon": "-2&demonFilter=3",
		"insanedemon": "-2&demonFilter=4",
		"extremedemon": "-2&demonFilter=5",
		"auto": "-3",
		"unrated": "-1",
		"na": "-1",
		"n/a": "-1"
	}
}
